pyiron_snippets/__init__.py
pyiron_snippets/_version.py
pyiron_snippets/colors.py
pyiron_snippets/deprecate.py
pyiron_snippets/dotdict.py
pyiron_snippets/exception_context.py
pyiron_snippets/factory.py
pyiron_snippets/files.py
pyiron_snippets/has_post.py
pyiron_snippets/import_alarm.py
pyiron_snippets/logger.py
pyiron_snippets/resources.py
pyiron_snippets/retrieve.py
pyiron_snippets/retry.py
pyiron_snippets/singleton.py
pyiron_snippets/tempenv.py
pyiron_snippets-1.0.2.dist-info/METADATA
pyiron_snippets-1.0.2.dist-info/WHEEL
pyiron_snippets-1.0.2.dist-info/licenses/LICENSE
pyiron_snippets-1.0.2.dist-info/RECORD
