Metadata-Version: 2.4
Name: pyiron_snippets
Version: 1.0.2
Summary: pyiron_snippets - Short, dependency-free python snippets.
Project-URL: Homepage, https://github.com/pyiron/pyiron_snippets
Project-URL: Documentation, https://pyiron-snippets.readthedocs.io
Project-URL: Repository, https://github.com/pyiron/pyiron_snippets
Author-email: Liam Huber <liamhuber@greyhavensolutions.com>, Sam Waseda <o.waseda@mpie.de>
License: BSD 3-Clause License
License-File: LICENSE
Keywords: pyiron
Classifier: Development Status :: 5 - Production/Stable
Classifier: Intended Audience :: Developers
Classifier: Intended Audience :: Science/Research
Classifier: License :: OSI Approved :: BSD License
Classifier: Operating System :: OS Independent
Classifier: Programming Language :: Python :: 3.11
Classifier: Programming Language :: Python :: 3.12
Classifier: Programming Language :: Python :: 3.13
Classifier: Programming Language :: Python :: 3.14
Classifier: Topic :: Scientific/Engineering
Classifier: Topic :: Software Development
Requires-Python: <3.15,>=3.11
Provides-Extra: tests
Requires-Dist: cloudpickle==3.1.1; extra == 'tests'
